mirlib/__init__.py
mirlib/etc/mir/area.yaml
mirlib/etc/mir/classes.yaml
mirlib/etc/mir/config.yaml
mirlib/etc/mir/grib-input.yaml
mirlib/etc/mir/grib-output-ii.yaml
mirlib/etc/mir/grib-output-iii.yaml
mirlib/etc/mir/grib-output.yaml
mirlib/etc/mir/grids.yaml
mirlib/etc/mir/netcdf.yaml
mirlib/etc/mir/parameter-class.yaml
mirlib/etc/mir/parameters.yaml
mirlib/etc/mir/style.yaml
mirlib/include/mir/mir_ecbuild_config.h
mirlib/include/mir/action/area/Area.h
mirlib/include/mir/action/area/AreaCropper.h
mirlib/include/mir/action/area/AreaMasker.h
mirlib/include/mir/action/calc/FormulaAction.h
mirlib/include/mir/action/context/Context.h
mirlib/include/mir/action/filter/AddRandomFilter.h
mirlib/include/mir/action/filter/AdjustWindsAtPoles.h
mirlib/include/mir/action/filter/AdjustWindsDirections.h
mirlib/include/mir/action/filter/AdjustWindsScaleCosLatitude.h
mirlib/include/mir/action/filter/Bandpass.h
mirlib/include/mir/action/filter/BitmapFilter.h
mirlib/include/mir/action/filter/CesaroSummationFilter.h
mirlib/include/mir/action/filter/FrameFilter.h
mirlib/include/mir/action/filter/GlobaliseFilter.h
mirlib/include/mir/action/filter/NablaFilter.h
mirlib/include/mir/action/filter/NablaFilterFVMT.h
mirlib/include/mir/action/filter/ShTruncate.h
mirlib/include/mir/action/filter/StatisticsFilter.h
mirlib/include/mir/action/filter/UnstructuredFilter.h
mirlib/include/mir/action/interpolate/Gridded2GridDef.h
mirlib/include/mir/action/interpolate/Gridded2GridSpec.h
mirlib/include/mir/action/interpolate/Gridded2GriddedInterpolation.h
mirlib/include/mir/action/interpolate/Gridded2NamedGrid.h
mirlib/include/mir/action/interpolate/Gridded2OctahedralGG.h
mirlib/include/mir/action/interpolate/Gridded2Points.h
mirlib/include/mir/action/interpolate/Gridded2ReducedGG.h
mirlib/include/mir/action/interpolate/Gridded2ReducedGGPLGiven.h
mirlib/include/mir/action/interpolate/Gridded2ReducedLL.h
mirlib/include/mir/action/interpolate/Gridded2ReducedLLPLGiven.h
mirlib-1.27.5.dist-info/licenses/AUTHORS
mirlib-1.27.5.dist-info/licenses/LICENSE
mirlib-1.27.5.dist-info/METADATA
mirlib-1.27.5.dist-info/WHEEL
mirlib-1.27.5.dist-info/top_level.txt
mirlib-1.27.5.dist-info/RECORD
