Metadata-Version: 2.4
Name: mirlib
Version: 1.27.5
Summary: "mirlib"
Author: file: AUTHORS
License-File: LICENSE
License-File: AUTHORS
Requires-Dist: eccodeslib<3,>=2.43.0
Requires-Dist: eckitlib<2,>=1.31.4
Requires-Dist: atlaslib-ecmwf<1,>=0.43.1
Dynamic: license-file
Dynamic: requires-dist
